thingsboard/__init__.py
thingsboard/common/__init__.py
thingsboard/common/version.py
thingsboard/common/core/__init__.py
thingsboard/common/core/thread_monitor.py
thingsboard/common/core/threaded.py
thingsboard/common/utils/__init__.py
thingsboard/common/utils/attribute_helpers.py
thingsboard/common/utils/datetime_helpers.py
thingsboard/common/utils/path_helpers.py
thingsboard/common/utils/resource_loader.py
thingsboard/common/utils/string_helpers.py
thingsboard/common/utils/timestamp_helpers.py
thingsboard_common-0.1.1.dist-info/licenses/LICENSE
thingsboard_common-0.1.1.dist-info/METADATA
thingsboard_common-0.1.1.dist-info/WHEEL
thingsboard_common-0.1.1.dist-info/top_level.txt
thingsboard_common-0.1.1.dist-info/RECORD
